[
  {
    "id": "p1",
    "name": "Paracetamol",
    "price": 20.0,
    "stock": 18,
    "category": "essential"
  },
  {
    "id": "p2",
    "name": "Insulin",
    "price": 150.0,
    "stock": 4,
    "category": "premium"
  },
  {
    "id": "f1",
    "name": "Sandwich",
    "price": 50.0,
    "stock": 19,
    "category": "general"
  },
  {
    "id": "f2",
    "name": "Juice",
    "price": 30.0,
    "stock": 18,
    "category": "general"
  },
  {
    "id": "e1",
    "name": "Water Bottle",
    "price": 10.0,
    "stock": 20,
    "category": "essential"
  },
  {
    "id": "e2",
    "name": "Energy Bar",
    "price": 15.0,
    "stock": 30,
    "category": "essential"
  }
]